relay_board_py/__init__.py
relay_board_py/__main__.py
relay_board_py/relay_board.py
relay_board_py/relay_board_hardware.py
relay_board_py/relay_board_pattern.py
relay_board_py/serial_interface.py
relay_board_py/serial_number.py
relay_board_py-0.3.dist-info/METADATA
relay_board_py-0.3.dist-info/WHEEL
relay_board_py-0.3.dist-info/licenses/LICENSE
relay_board_py-0.3.dist-info/RECORD
