Metadata-Version: 2.3
Name: relay_board_py
Version: 0.3
Summary: Python package to interact with relay board
Project-URL: Homepage, https://github.com/embforge/relay-board-py
Project-URL: Documentation, https://github.com/embforge/relay-board-py/tree/main/doc
Project-URL: Changelog, https://github.com/embforge/relay-board-py/blob/main/CHANGELOG.md
Author-email: Michael Hopfengaertner <michael.hopfengaertner@gmx.net>
License-Expression: MIT
License-File: LICENSE
Classifier: License :: OSI Approved :: MIT License
Classifier: Operating System :: OS Independent
Classifier: Programming Language :: Python :: 3
Requires-Python: >=3.8
Requires-Dist: pyserial>=3.4
